cave_mapper/__init__.py
cave_mapper/mapping.py
cave_mapper-0.2.0.dist-info/METADATA
cave_mapper-0.2.0.dist-info/WHEEL
cave_mapper-0.2.0.dist-info/RECORD
