Metadata-Version: 2.4
Name: cave-mapper
Version: 0.2.0
Summary: Tools for mapping between objects and representations in the CAVE ecosystem
Project-URL: Homepage, https://bdpedigo.github.io/cave-mapper/
Project-URL: Issues, https://github.com/bdpedigo/cave-mapper/issues
Project-URL: Repository, https://github.com/bdpedigo/cave-mapper.git
Author-email: Ben Pedigo <benjamindpedigo@gmail.com>
License-Expression: MIT
Requires-Python: <3.13,>=3.10
Requires-Dist: caveclient[cv]>=7.7.0
Requires-Dist: mkdocs-material>=9.6.11
Requires-Dist: mkdocs>=1.6.1
Requires-Dist: point-cloud-utils>=0.34.0
